closeformIK/CloseFormIK.cp39-win_amd64.pyd
closeformIK/CloseFormIK.cpython-39-x86_64-linux-gnu.so
closeformIK/__init__.py
closeformIK-1.0.8.dist-info/METADATA
closeformIK-1.0.8.dist-info/WHEEL
closeformIK-1.0.8.dist-info/top_level.txt
closeformIK-1.0.8.dist-info/RECORD
