Metadata-Version: 2.1
Name: closeformIK
Version: 1.0.8
Summary: robot6Ik Package with dynamic libraries for both Linux and Windows
Home-page: https://github.com/Frank/closeformIK
Author: Frank
Classifier: Programming Language :: Python :: 3
Classifier: Operating System :: OS Independent
Requires-Python: >=3.9
Requires-Dist: numpy
Requires-Dist: scipy
